{
    "version": 0,
    "page": 7225,
    "commands": [
        {
            "command": "[A6A6I4] ====> ",
            "link": "/story/7226"
        }
    ],
    "media": [
        {
            "file": "07222.gif",
            "folder": "0"
        }
    ],
    "text": null,
    "pesterlog": "<p style=\"color: #0715cd\">JOHN: it feels good to have it back.</p>\n<p style=\"color: #0715cd\">JOHN: the dear, sweet, precious ring of ghost life...</p>\n<p style=\"color: #0715cd\">JOHN: i'll never lose track of it again!</p>\n<p style=\"color: #0715cd\">JOHN: i definitely won't let...</p>\n<p style=\"color: #0715cd\">JOHN: um...</p>\n<p style=\"color: #0715cd\">JOHN: wait, who was going to steal this ring again?</p>\n<p style=\"color: #0715cd\">JOHN: the other vriska, with the short pirate skirt... what was her name?</p>\n<p style=\"color: #0715cd\">JOHN: meh, it doesn't matter. she's probably irrelevant now.</p>",
    "flash": false,
    "javascript": false,
    "author": "THE HUSS",
    "commited": true
}