{
    "version": 0,
    "page": 7730,
    "commands": [
        {
            "command": "[A6A6I5] ====> ",
            "link": "/story/7731"
        }
    ],
    "media": [
        {
            "file": "07726.gif",
            "folder": "0"
        }
    ],
    "text": null,
    "pesterlog": "<p style=\"color: #ff6ff2\">ROXY: so</p>\n<p style=\"color: #ff6ff2\">ROXY: yeah</p>\n<p style=\"color: #ff6ff2\">ROXY: if we make it thru this</p>\n<p style=\"color: #ff6ff2\">ROXY: ill come back for you</p>\n<p style=\"color: #ff6ff2\">ROXY: and then</p>\n<p style=\"color: #ff6ff2\">ROXY: we figure out what happens next!</p>\n<p style=\"color: #929292\">CALLIOPE: i can't wait.</p>\n<p style=\"color: #ff6ff2\">ROXY: hope ur not sick of hearin it yet</p>\n<p style=\"color: #ff6ff2\">ROXY: but im still so psyched youre with us</p>\n<p style=\"color: #929292\">CALLIOPE: of coUrse i'm not sick of it!</p>\n<p style=\"color: #ff6ff2\">ROXY: it is just</p>\n<p style=\"color: #ff6ff2\">ROXY: errgh</p>\n<p style=\"color: #929292\">CALLIOPE: ?</p>\n<p style=\"color: #ff6ff2\">ROXY: callie in times such as these...</p>\n<p style=\"color: #ff6ff2\">ROXY: ya know</p>\n<p style=\"color: #ff6ff2\">ROXY: words have trouble cuttin it</p>\n<p style=\"color: #ff6ff2\">ROXY: ca'mere</p>",
    "flash": false,
    "javascript": false,
    "author": "THE HUSS",
    "commited": true
}