{
    "version": 0,
    "page": 5033,
    "commands": [
        {
            "command": "Select character. ",
            "link": "/story/5034"
        }
    ],
    "media": [
        {
            "file": "05030.gif",
            "folder": "0"
        }
    ],
    "text": null,
    "pesterlog": "<p style=\"color: #929292\">uranianUmbra [UU]</span> began cheering <span style=\"color: #323232\">undyingUmbrage [uu]</p>\n<p style=\"color: #929292\">UU: FUCK THIS!!!!!!!!!!!</p>\n<p style=\"color: #929292\">UU: i don't know why i bothered hUmoUring yoUr vile Underhanded rUbbish!</p>\n<p style=\"color: #929292\">UU: I HATE YOU. JUST SOD RIGHT OFF TO HELL, PLEASE.</p>\n<p style=\"color: #929292\">uranianUmbra [UU]</span> ceased cheering <span style=\"color: #323232\">undyingUmbrage [uu]</p>\n\n<p style=\"color: #323232\">undyingUmbrage [uu]</span> began jeering <span style=\"color: #929292\">uranianUmbra [UU]</p>\n<p style=\"color: #323232\">uu: HEY THERE. BE CAREFuL.</p>\n<p style=\"color: #323232\">uu: A GuY COuLD GET THE WRONG IDEA. AND MISTAKE YOuR OuTBuRST FOR SOMETHING.</p>\n<p style=\"color: #323232\">uu: CALIGINOuS.</p>\n<p style=\"color: #323232\">uu: THAT WOuLD BE MOST uN\"SISTERLY.\" DON'T YOu THINK.</p>\n<p style=\"color: #323232\">uu: ANYWAY. BY THE LOOKS OF THIS MESSY BOARD.</p>\n<p style=\"color: #323232\">uu: I'M GOING TO ASSuME YOu FORFEITED THE MATCH.</p>\n<p style=\"color: #323232\">undyingUmbrage [uu]</span> ceased jeering <span style=\"color: #929292\">uranianUmbra [UU]</p>\n\n<p style=\"color: #929292\">uranianUmbra [UU]</span> began cheering <span style=\"color: #323232\">undyingUmbrage [uu]</p>\n<p style=\"color: #929292\">UU: yoU are disgUsting.</p>\n<p style=\"color: #929292\">UU: i really loathe yoU, and no, NOT IN \"THAT WAY!\"</p>\n<p style=\"color: #929292\">UU: i am not going to talk to yoU for a while. probably a LONG while.</p>\n<p style=\"color: #929292\">UU: i only hope i can overcome my contempt for yoU when it comes time to play oUr game. bUt i am not holding my breath!!!!!!!!!!!</p>\n<p style=\"color: #929292\">UU: leave me alone.</p>\n<p style=\"color: #929292\">uranianUmbra [UU]</span> blocked <span style=\"color: #323232\">undyingUmbrage [uu]</p>\n\n<p style=\"color: #323232\">undyingUmbrage [uu]</span> began jeering <span style=\"color: #929292\">uranianUmbra [UU]</p>\n<p style=\"color: #323232\">uu: YOu BLOCKED ME AGAIN? YOu KNOW THAT DOESN'T DO ANYTHING.</p>\n<p style=\"color: #323232\">uu: ANYWAY. I'M HAPPY WE ARE IN AGREEMENT THAT I WON.</p>\n<p style=\"color: #323232\">uu: YOu SHOuLDN'T uNDERESTIMATE ME.</p>\n<p style=\"color: #323232\">uu: I'LL LEAVE YOu ALONE FOR A WHILE LIKE YOu WANT. BECAuSE REALLY. WHO CARES ABOuT YOu?</p>\n<p style=\"color: #323232\">uu: BuT YOu SHOuLD BELIEVE ME.</p>\n<p style=\"color: #323232\">uu: WHEN I TELL YOu.</p>\n<p style=\"color: #323232\">uu: SOME DAY.</p>\n<p style=\"color: #323232\">uu: I'M GOING TO KILL YOu IN YOuR SLEEP.</p>\n<p style=\"color: #323232\">uu: MAYBE EVEN.</p>\n<p style=\"color: #323232\">uu: MORE THAN ONCE.</p>\n<p style=\"color: #323232\">undyingUmbrage [uu]</span> ceased jeering <span style=\"color: #929292\">uranianUmbra [UU]</p>",
    "flash": false,
    "javascript": false,
    "author": "THE HUSS",
    "commited": true
}