{
    "version": 0,
    "page": 3244,
    "commands": [
        {
            "command": "==> ",
            "link": "/story/3245"
        }
    ],
    "media": [
        {
            "file": "03241.gif",
            "folder": "0"
        }
    ],
    "text": null,
    "pesterlog": "<p style=\"color: #1f9400\">JADESPRITE: i dont want to be here, i have to go back</p>\n<p style=\"color: #1f9400\">JADESPRITE: but i dont know how</p>\n<p style=\"color: #1f9400\">JADESPRITE: can you help me?</p>\n<p style=\"color: #4ac925\">JADE: you want me to help you...</p>\n<p style=\"color: #4ac925\">JADE: die again?</p>\n<p style=\"color: #1f9400\">JADESPRITE: yes, i think thats what i would like</p>\n<p style=\"color: #1f9400\">JADESPRITE: i cant take this, i wasnt ready to come back</p>\n<p style=\"color: #1f9400\">JADESPRITE: not like this</p>\n<p style=\"color: #4ac925\">JADE: wow...</p>\n<p style=\"color: #4ac925\">JADE: ok, i know this is my fault</p>\n<p style=\"color: #4ac925\">JADE: but that is a really hard thing to ask me to do!</p>\n<p style=\"color: #4ac925\">JADE: even if it was possible the way you are now</p>\n<p style=\"color: #4ac925\">JADE: i dont think i could go through with it :(</p>\n<p style=\"color: #1f9400\">JADESPRITE: boo hoo hoo hoo hoo</p>\n<p style=\"color: #4ac925\">JADE: ok ok shhhhh...</p>\n<p style=\"color: #4ac925\">JADE: jade listen</p>\n<p style=\"color: #4ac925\">JADE: i never did tell you why i brought you back</p>\n<p style=\"color: #4ac925\">JADE: and it may be that</p>\n<p style=\"color: #4ac925\">JADE: if you attempt what i wanted you to do in the first place</p>\n<p style=\"color: #4ac925\">JADE: god i cant believe im saying this...</p>\n<p style=\"color: #4ac925\">JADE: but you might end up getting what you want anyway</p>\n<p style=\"color: #4ac925\">JADE: because it was always going to be risky</p>\n<p style=\"color: #1f9400\">JADESPRITE: what is it?</p>\n<p style=\"color: #4ac925\">JADE: well, you remember the guy who destroyed prospit?</p>\n<p style=\"color: #1f9400\">JADESPRITE: oh god D:</p>\n<p style=\"color: #1f9400\">JADESPRITE: ohh god noooooo...</p>\n<p style=\"color: #4ac925\">JADE: shh!!!</p>\n<p style=\"color: #4ac925\">JADE: anyway, he is the reason i brought you here</p>\n<p style=\"color: #4ac925\">JADE: he has the same powers you have, making him unbeatable to us...</p>\n<p style=\"color: #4ac925\">JADE: but maybe not you!</p>\n<p style=\"color: #4ac925\">JADE: so you could go find him and</p>\n<p style=\"color: #1f9400\">JADESPRITE: you want me to fight him???</p>\n<p style=\"color: #4ac925\">JADE: um</p>\n<p style=\"color: #1f9400\">JADESPRITE: are you crazy? do i look like i am ready to fight anybody???????</p>\n<p style=\"color: #4ac925\">JADE: i just thought</p>\n<p style=\"color: #4ac925\">JADE: as long as youre here</p>\n<p style=\"color: #1f9400\">JADESPRITE: i cant fight anybody!</p>\n<p style=\"color: #1f9400\">JADESPRITE: jade i am scared and confused and sad and...</p>\n<p style=\"color: #1f9400\">JADESPRITE: i wouldnt even know how to begin fighting that horrible guy</p>\n<p style=\"color: #1f9400\">JADESPRITE: i would be too afraid of him to even go find him</p>\n<p style=\"color: #4ac925\">JADE: but</p>\n<p style=\"color: #4ac925\">JADE: i thought you wanted to die?</p>\n<p style=\"color: #4ac925\">JADE: you wouldnt go even if he could...</p>\n<p style=\"color: #1f9400\">JADESPRITE: no i dont want him to kill me!!!</p>\n<p style=\"color: #1f9400\">JADESPRITE: you just dont understand aaaaa boo hoo hoo</p>\n<p style=\"color: #4ac925\">JADE: jeez...</p>\n<p style=\"color: #4ac925\">JADE: youre right, i really dont</p>\n<p style=\"color: #1f9400\">JADESPRITE: BOO HOO HOO HOO</p>\n<p style=\"color: #4ac925\">JADE: i said SHH!</p>\n<p style=\"color: #4ac925\">JADE: wow</p>\n<p style=\"color: #4ac925\">JADE: jade...</p>\n<p style=\"color: #4ac925\">JADE: i dont mean to be insensitive but</p>\n<p style=\"color: #4ac925\">JADE: there is a lot at stake here!</p>\n<p style=\"color: #1f9400\">JADESPRITE: woof</p>\n<p style=\"color: #4ac925\">JADE: i... pfhehe, dont change the subject!</p>\n<p style=\"color: #4ac925\">JADE: i mean, dont you remember what this was all about?</p>\n<p style=\"color: #4ac925\">JADE: what you were working for... what WE were working for all those years before you died?</p>\n<p style=\"color: #4ac925\">JADE: remember what we saw in the clouds, or what the queen told us?</p>\n<p style=\"color: #1f9400\">JADESPRITE: uh...</p>\n<p style=\"color: #4ac925\">JADE: how could you not remember john survived?</p>\n<p style=\"color: #4ac925\">JADE: we both saw him in a cloud! he was in his dream suit and awake, reading our letter!</p>\n<p style=\"color: #4ac925\">JADE: didnt you think about that?</p>\n<p style=\"color: #1f9400\">JADESPRITE: ummmm, so? what does it matter?</p>\n<p style=\"color: #4ac925\">JADE: ...</p>\n<p style=\"color: #1f9400\">JADESPRITE: it was all a lie jade. what we saw in the clouds and all that. none of it meant anything</p>\n<p style=\"color: #4ac925\">JADE: what!!!!!</p>\n<p style=\"color: #4ac925\">JADE: how can you SAY that?</p>\n<p style=\"color: #1f9400\">JADESPRITE: it was a nice life, but everything we did lead to nothing</p>\n<p style=\"color: #1f9400\">JADESPRITE: john and i both died, and i eventually accepted that and moved on</p>\n<p style=\"color: #4ac925\">JADE: JOHN DIDNT DIE!!!</p>\n<p style=\"color: #4ac925\">JADE: omg...</p>\n<p style=\"color: #4ac925\">JADE: this is so frustrating, i just told you he didnt</p>\n<p style=\"color: #4ac925\">JADE: i knew i was kind of ditzy and forgetful in my dreams, but</p>\n<p style=\"color: #1f9400\">JADESPRITE: boooo ho-</p>\n<p style=\"color: #4ac925\">JADE: SHHHHH! okaaaaaay, jeez!</p>\n<p style=\"color: #4ac925\">JADE: i just dont know what to think</p>\n<p style=\"color: #4ac925\">JADE: i guess you are part of me, and you are who i was when i slept</p>\n<p style=\"color: #4ac925\">JADE: but it makes me sad to think i would act like this</p>\n<p style=\"color: #1f9400\">JADESPRITE: act like what?</p>\n<p style=\"color: #4ac925\">JADE: i would like to think that even if i was sad and scared, if i was put in a position where everyone depended on me, i could put all those feelings aside and do whats right!</p>\n<p style=\"color: #1f9400\">JADESPRITE: but i dont know whats right</p>\n<p style=\"color: #4ac925\">JADE: yes you do!</p>\n<p style=\"color: #4ac925\">JADE: even though you dont want to be, youre here now, and there are still people who need you</p>\n<p style=\"color: #4ac925\">JADE: there is still something worth fighting for!</p>",
    "flash": false,
    "javascript": false,
    "author": "THE HUSS",
    "commited": true
}