{
    "version": 0,
    "page": 4729,
    "commands": [
        {
            "command": "[A6I2] ==> ",
            "link": "/story/4730"
        }
    ],
    "media": [
        {
            "file": "04726.gif",
            "folder": "0"
        }
    ],
    "text": null,
    "pesterlog": "<p style=\"color: #4ac925\">JADE: john i really think we are scraping the bottom of the barrel here</p>\n<p style=\"color: #0715cd\">JOHN: no way! this game rules.</p>\n<p style=\"color: #0715cd\">JOHN: i just never gave it much playing time before because...</p>\n<p style=\"color: #0715cd\">JOHN: well, i guess i always had better things to do.</p>\n<p style=\"color: #4ac925\">JADE: thats sort of my point!</p>\n<p style=\"color: #4ac925\">JADE: where did you even get this?</p>\n<p style=\"color: #0715cd\">JOHN: years ago i found it in a store on the bargain rack.</p>\n<p style=\"color: #0715cd\">JOHN: it was only a dollar! isn't that awesome?</p>\n<p style=\"color: #4ac925\">JADE: :|</p>",
    "flash": false,
    "javascript": false,
    "author": "THE HUSS",
    "commited": true
}