{
    "version": 0,
    "page": 7480,
    "commands": [
        {
            "command": "[A6A6I5] ====> ",
            "link": "/story/7481"
        }
    ],
    "media": [
        {
            "file": "07476.gif",
            "folder": "0"
        }
    ],
    "text": null,
    "pesterlog": "<p style=\"color: #008282\">TEREZI: 1 W4S 4LMOST C3RT41NLY FUCK1NG W1TH YOU</p>\n<p style=\"color: #0715cd\">JOHN: ok, wow. great.</p>\n<p style=\"color: #0715cd\">JOHN: good to know.</p>\n<p style=\"color: #0715cd\">JOHN: thanks for that, terezi. that was a really awesome use of our time.</p>\n<p style=\"color: #008282\">TEREZI: 1'M GL4D W3 4R3 1N COMPL3T3 4GR33M3NT</p>\n<p style=\"color: #005682\">VRISKA: W8, what?</p>\n<p style=\"color: #005682\">VRISKA: What's this a8out stuffed dragons?</p>\n<p style=\"color: #005682\">VRISKA: Terezi, what stupid thing did you make John do?</p>\n<p style=\"color: #008282\">TEREZI: 1 JUST S3NT H1M ON 4 F3W TOT4LLY 1ND1SP3NS1BL3, M1SS1ON CR1T1C4L 3RR4NDS 1S 4LL</p>\n<p style=\"color: #008282\">TEREZI: NO B1G D34L</p>\n<p style=\"color: #0715cd\">JOHN: yeah, forget it.</p>\n<p style=\"color: #0715cd\">JOHN: long story short is, i got owned, the end.</p>\n<p style=\"color: #0715cd\">JOHN: by the way, good to see you again vriska!</p>\n<p style=\"color: #005682\">VRISKA: Good to see you too, John!</p>\n<p style=\"color: #0715cd\">JOHN: it's cool that you're alive now, instead of being a cunning ghost pirate.</p>\n<p style=\"color: #0715cd\">JOHN: i think your, um, *ways* probably are more valuable to have here, in the land of the living.</p>\n<p style=\"color: #0715cd\">JOHN: at least... i hope so??</p>\n<p style=\"color: #005682\">VRISKA: I couldn't agree more!</p>\n<p style=\"color: #005682\">VRISKA: I never got a chance to thank you for knocking me out a few years ago. I mean... o8viously? 8ecause I was unconscious.</p>\n<p style=\"color: #005682\">VRISKA: 8ut thanks for that. I was 8eing an idiot, and deserved it.</p>\n<p style=\"color: #005682\">VRISKA: And as a 8onus, it apparently saved my life???????? So, thanks.</p>\n<p style=\"color: #005682\">VRISKA: You're a real friend. ::::)</p>\n<p style=\"color: #0715cd\">JOHN: don't mention it!</p>\n<p style=\"color: #005682\">VRISKA: I've received quite a few 8eatings in my time, and not only did I have each one coming, 8ut they all led to 8ig changes for me, on the road to 8ecoming the impecca8ly evolved person I am now.</p>\n<p style=\"color: #005682\">VRISKA: So 8y that measure, it was pro8a8ly the most critical smackdown of my entire life!</p>\n<p style=\"color: #0715cd\">JOHN: that's cool.</p>\n<p style=\"color: #0715cd\">JOHN: if you ever need another really important punch in the face, just let me know. i'm your man.</p>",
    "flash": false,
    "javascript": false,
    "author": "THE HUSS",
    "commited": true
}