{
    "version": 0,
    "page": 5039,
    "commands": [
        {
            "command": "==> ",
            "link": "/story/5040"
        }
    ],
    "media": [
        {
            "file": "05036.gif",
            "folder": "0"
        }
    ],
    "text": null,
    "pesterlog": "<p style=\"color: #00d5f2\">GG: OH NO!!!!!</p>\n<p style=\"color: #00d5f2\">GG: Roxy, where are you??? :(</p>\n<p style=\"color: #e00707\">TT: We'll track her down.</p>\n<p style=\"color: #e00707\">TT: The important thing to do now is deploy all the devices quickly, so the house will be ready to jet the moment she gets back.</p>\n<p style=\"color: #00d5f2\">GG: How do you know she's not hurt?</p>\n<p style=\"color: #e00707\">TT: That is statistically remote.</p>\n<p style=\"color: #e00707\">TT: Given that I can track the coordinates of certain devices she carries, and they are presently in motion.</p>\n<p style=\"color: #e00707\">TT: Really, the fire is not the most significant threat, or even the drones.</p>\n<p style=\"color: #00d5f2\">GG: Then what is?</p>\n<p style=\"color: #e00707\">TT: Do you see the red stringy stuff coming from the sky?</p>\n<p style=\"color: #00d5f2\">GG: Oh...</p>\n<p style=\"color: #00d5f2\">GG: Yes.</p>\n<p style=\"color: #00d5f2\">GG: What IS that??</p>",
    "flash": false,
    "javascript": false,
    "author": "THE HUSS",
    "commited": true
}