{
    "version": 0,
    "page": 6788,
    "commands": [
        {
            "command": "[A6A6I2] ====> ",
            "link": "/story/6789"
        }
    ],
    "media": [
        {
            "file": "06785.gif",
            "folder": "0"
        }
    ],
    "text": null,
    "pesterlog": "<p style=\"color: #2b0057\">GAMZEE:\n<img border=\"0\" src=\"/images/storyfiles/hs2/scraps/BLOODHONK.gif\"/></p>",
    "flash": false,
    "javascript": false,
    "author": "THE HUSS",
    "commited": true
}