{
    "version": 0,
    "page": 7415,
    "commands": [
        {
            "command": "ONE MORE BANNER PIECE OF SWAG IN MY POSSESSION. ",
            "link": "/story/7416"
        }
    ],
    "media": [
        {
            "file": "07412.swf",
            "folder": "0"
        }
    ],
    "text": "<p class=\"o-story_text type-rg type-hs-small--md type-center line-caption line-copy--md pad-x-0 pad-x-lg--md pad-b-lg\">I'VE GOT MY JUJU CHEST THERE. WHICH I WILL WIN AS SOME CHOICE BOOTY, FROM VICTORIOUSLY SLAUGHTERING MY DENIZEN. KING YALDOBOB. INSIDE IS A MIGHTY WEAPON. WHICH WILL COME INTO PLAY A LITTLE LATER. IN MY THEATER OF WOBBLING PUPPET DRAMA. IT'S LIKE THEY SAY ABOUT THE THEATER. IF YOU SEE A JUJU IN ACT ONE. THEN THE JUJU WILL PROBABLY BE USED RIGHT AWAY IN ACT ONE. TO MAKE EVERYTHING MORE EXCITING, AS SOON AS POSSIBLE. \r<br/> <br/>ALSO, WHICH I SHOULD MENTION...</p>",
    "pesterlog": null,
    "flash": true,
    "javascript": false,
    "author": "THE HUSS",
    "commited": true
}