{
    "version": 0,
    "page": 6653,
    "commands": [
        {
            "command": "[A6A6I2] ====> ",
            "link": "/story/6654"
        }
    ],
    "media": [
        {
            "file": "06650.gif",
            "folder": "0"
        }
    ],
    "text": null,
    "pesterlog": "<p style=\"color: #e00707\">DAVE: alright mayor</p>\n<p style=\"color: #e00707\">DAVE: ive got to go now</p>\n<p style=\"color: #e00707\">DAVE: not sure why but</p>\n<p style=\"color: #e00707\">DAVE: i have a really bad feeling about all this</p>\n<p style=\"color: #e00707\">DAVE: i mean</p>\n<p style=\"color: #e00707\">DAVE: i dont wanna scare you or come off as too dramatic or anything</p>\n<p style=\"color: #e00707\">DAVE: but</p>\n<p style=\"color: #e00707\">DAVE: if i never see you again i just wanted you to know</p>\n<p style=\"color: #e00707\">DAVE: its been real man</p>\n<p style=\"color: #e00707\">DAVE: you were always there for me</p>\n<p style=\"color: #e00707\">DAVE: you shared my darkest hours</p>\n<p style=\"color: #e00707\">DAVE: my deepest secrets</p>\n<p style=\"color: #e00707\">DAVE: and ill never fucking forget it</p>\n<p style=\"color: #e00707\">DAVE: goodbye mayor</p>",
    "flash": false,
    "javascript": false,
    "author": "THE HUSS",
    "commited": true
}