{
    "version": 0,
    "page": 4604,
    "commands": [
        {
            "command": "==> ",
            "link": "/story/4605"
        }
    ],
    "media": [
        {
            "file": "04601.gif",
            "folder": "0"
        }
    ],
    "text": "<p class=\"o-story_text type-rg type-hs-small--md type-center line-caption line-copy--md pad-x-0 pad-x-lg--md pad-b-lg\">More noises echoing in the distance. Some of the meowcats get nervous and poof up their tails.\r<br/> <br/>It's pretty clear you aren't alone in here. Better make this quick.</p>",
    "pesterlog": null,
    "flash": false,
    "javascript": false,
    "author": "THE HUSS",
    "commited": true
}