{
    "version": 0,
    "page": 7105,
    "commands": [
        {
            "command": "[A6A6I4] ====> ",
            "link": "/story/7106"
        }
    ],
    "media": [
        {
            "file": "07102.gif",
            "folder": "0"
        }
    ],
    "text": null,
    "pesterlog": "<p style=\"color: #0715cd\">JOHN: i'm glad it worked out like this.</p>\n<p style=\"color: #0715cd\">JOHN: i was fully prepared to do this alone... to hop around and change things in whatever way.</p>\n<p style=\"color: #0715cd\">JOHN: and i would get to see my friends again, even if they don't remember all the same stuff i do.</p>\n<p style=\"color: #0715cd\">JOHN: which was a lonely feeling, if that makes sense?</p>\n<p style=\"color: #0715cd\">JOHN: but now i'll have someone else to remember the way things originally went.</p>\n<p style=\"color: #ff6ff2\">ROXY: word</p>\n<p style=\"color: #0715cd\">JOHN: yes. word indeed.</p>\n<p style=\"color: #ff6ff2\">ROXY: but i know what you mean</p>\n<p style=\"color: #ff6ff2\">ROXY: its nice to have uh</p>\n<p style=\"color: #ff6ff2\">ROXY: like a witness i guess?</p>\n<p style=\"color: #ff6ff2\">ROXY: someone to authenticate the rough shit u went through</p>\n<p style=\"color: #ff6ff2\">ROXY: even if we never end up talkin about it again</p>\n<p style=\"color: #ff6ff2\">ROXY: the fact that at least SOMEONE else knows</p>\n<p style=\"color: #ff6ff2\">ROXY: makes it feel like it didnt all mean</p>\n<p style=\"color: #ff6ff2\">ROXY: nothing?</p>\n<p style=\"color: #0715cd\">JOHN: right.</p>\n<p style=\"color: #ff6ff2\">ROXY: because even if it all gets erased and put back all better</p>\n<p style=\"color: #ff6ff2\">ROXY: i dont think the stuff we went through and the feelings we had meant nothing</p>\n<p style=\"color: #ff6ff2\">ROXY: imo the feelings themselves</p>\n<p style=\"color: #ff6ff2\">ROXY: and the way they shaped us</p>\n<p style=\"color: #ff6ff2\">ROXY: that all means...</p>\n<p style=\"color: #ff6ff2\">ROXY: somethin</p>\n<p style=\"color: #0715cd\">JOHN: ...</p>\n<p style=\"color: #ff6ff2\">ROXY: hahaha forget it</p>\n<p style=\"color: #ff6ff2\">ROXY: talkin out my ass here</p>\n<p style=\"color: #0715cd\">JOHN: no, it makes sense.</p>\n<p style=\"color: #0715cd\">JOHN: and anyway, if nothing else, everything that happened brought us here.</p>\n<p style=\"color: #0715cd\">JOHN: the stuff we're about to do, whatever it is, wouldn't be possible otherwise.</p>\n<p style=\"color: #0715cd\">JOHN: and that feels pretty important, if you ask me!</p>",
    "flash": false,
    "javascript": false,
    "author": "THE HUSS",
    "commited": true
}