{
    "version": 0,
    "page": 6623,
    "commands": [
        {
            "command": "[A6A6I2] ====> ",
            "link": "/story/6624"
        }
    ],
    "media": [
        {
            "file": "06620.gif",
            "folder": "0"
        }
    ],
    "text": null,
    "pesterlog": "<p class=\"o_chat-log type-left type-rg type-hs-small--md line-caption line-copy--md mar-t-md mar-t-md--md pad-x-md pad-x-hs-lg--md pad-b-md pad-b-md--md disp-n\"><img border=\"0\" src=\"/images/storyfiles/hs2/scraps/karkat_blurtext1.gif\"/>\n<p style=\"color: #e00707\">DAVE: what?</p>\n<img border=\"0\" src=\"/images/storyfiles/hs2/scraps/karkat_blurtext2.gif\"/>\n<p style=\"color: #e00707\">DAVE: what was that</p>\n<img border=\"0\" src=\"/images/storyfiles/hs2/scraps/karkat_blurtext3.gif\"/>\n<p style=\"color: #e00707\">DAVE: dude your words are all muffled</p>\n<p style=\"color: #e00707\">DAVE: can you speak up</p>\n<img border=\"0\" src=\"/images/storyfiles/hs2/scraps/karkat_blurtext4.gif\"/>\n<p style=\"color: #e00707\">DAVE: louder</p>\n<img border=\"0\" src=\"/images/storyfiles/hs2/scraps/karkat_blurtext5.gif\"/>\n<p style=\"color: #e00707\">DAVE: louder man</p>\n<p style=\"color: #e00707\">DAVE: sound doesnt travel through foam too well</p>",
    "flash": false,
    "javascript": false,
    "author": "THE HUSS",
    "commited": true
}