{
    "version": 0,
    "page": 2365,
    "commands": [
        {
            "command": "And again, in time... ",
            "link": "/story/2366"
        }
    ],
    "media": [
        {
            "file": "02365_1.gif",
            "folder": "0"
        },
        {
            "file": "02365_2.gif",
            "folder": "0"
        }
    ],
    "text": null,
    "pesterlog": "<p style=\"color: #005682\">AG: Flyyyyyyyy!</span></p>",
    "flash": false,
    "javascript": false,
    "author": "THE HUSS",
    "commited": true
}