{
    "version": 0,
    "page": 2789,
    "commands": [
        {
            "command": "John and Dave: Respond to memo. ",
            "link": "/story/2790"
        }
    ],
    "media": [
        {
            "file": "02788.gif",
            "folder": "0"
        }
    ],
    "text": null,
    "pesterlog": "<p class=\"o_chat-log type-left type-rg type-hs-small--md line-caption line-copy--md mar-t-md mar-t-md--md pad-x-md pad-x-hs-lg--md pad-b-md pad-b-md--md disp-n\">carcinoGeneticist <span style=\"color: #626262\">[CG]</span> began trolling turntechGodhead <span style=\"color: #e00707\">[TG]</p>\n\n<p style=\"color: #626262\">CG: HEY SHITHEAD YOU ARE IN HUGE TROUBLE.</p>\n<p style=\"color: #626262\">CG: A WORD WITH YOU AND YOUR FRIEND.</p>\n<p style=\"color: #e00707\">TG: i thought you were asleep</p>\n<p style=\"color: #626262\">CG: YES DAVE, I WAS ASLEEP AT ONE POINT.</p>\n<p style=\"color: #626262\">CG: IT STANDS TO REASON I AM NOW AND WILL ALWAYS BE ASLEEP AT EVERY POINT ON ALL TIMELINES.</p>\n<p style=\"color: #626262\">CG: THAT REALLY MAKES A LOT OF FUCKING SENSE.</p>\n<p style=\"color: #626262\">CG: NOW YOU, ME, AND EGBERT NEED TO HAVE A CHAT.</p>\n<p style=\"color: #626262\">CG: HERE I MADE A COOL BANNER USING SOME OF YOUR SHITTY EARTH CLIP ART.</p>\n<p style=\"color: #626262\">CG: CLICK IT.</p>\n<p style=\"color: #626262\">CG: <img border=\"0\" src=\"/images/storyfiles/hs2/scraps/FRUITYRUMPUSASSHOLEFACTORY.gif\"/></p>\n<p style=\"color: #e00707\">TG: not cool</p>\n<p style=\"color: #e00707\">TG: luring me into your cyber boobytrap with shitty clip art who told you my weakness</p>\n<p style=\"color: #626262\">CG: IT'LL WORK, WON'T IT?</p>\n<p style=\"color: #e00707\">TG: obviously</p>",
    "flash": false,
    "javascript": false,
    "author": "THE HUSS",
    "commited": true
}