{
    "version": 0,
    "page": 4923,
    "commands": [
        {
            "command": "Jack: Quick, be the other guy again. ",
            "link": "/story/4924"
        }
    ],
    "media": [
        {
            "file": "04920.gif",
            "folder": "0"
        }
    ],
    "text": "<p class=\"o-story_text type-rg type-hs-small--md type-center line-caption line-copy--md pad-x-0 pad-x-lg--md pad-b-lg\">Ah. You see. It appears there are quite a few said gluttons this time. Settle down, gentlemen. There are more than enough face bashings to go around.</p>",
    "pesterlog": null,
    "flash": false,
    "javascript": false,
    "author": "THE HUSS",
    "commited": true
}