{
    "version": 0,
    "page": 5004,
    "commands": [
        {
            "command": "==> ",
            "link": "/story/5005"
        }
    ],
    "media": [
        {
            "file": "05001.gif",
            "folder": "0"
        }
    ],
    "text": null,
    "pesterlog": "<p style=\"color: #1f9400\">JAKE: (Great scott!)</p>\n<p style=\"color: #1f9400\">JAKE: (I have to do something.)</p>\n<p style=\"color: #f2a400\">DIRK: Do something?</p>\n<p style=\"color: #f2a400\">DIRK: No, man. Just sit tight, ok?</p>\n<p style=\"color: #1f9400\">JAKE: (But thats sea hitler! Shes right there in the spooky flesh!)</p>\n<p style=\"color: #1f9400\">JAKE: (Remember all the horrible things you said she did??)</p>\n<p style=\"color: #f2a400\">DIRK: Yeah, but...</p>\n<p style=\"color: #1f9400\">JAKE: (Cripes it sets my blood aboil just thinking about it.)</p>\n<p style=\"color: #1f9400\">JAKE: (I have to stop her! Thats why im here i just figured it out. I have to do it bro!)</p>\n<p style=\"color: #f2a400\">DIRK: No you don't. Come on, don't be an idiot.</p>\n<p style=\"color: #1f9400\">JAKE: (Yes i do thats what you do when you go back in time and find hitler.)</p>\n<p style=\"color: #1f9400\">JAKE: (Thats like one of the rules of adventure if you have the chance to kill hitler and stop his crimes from happening then you do it!)</p>\n<p style=\"color: #1f9400\">JAKE: (Oh man oh man oh man...)</p>\n<p style=\"color: #f2a400\">DIRK: You didn't go back in time, Jake. Do you even understand what's going on?</p>\n<p style=\"color: #1f9400\">JAKE: (I gotta do something ok ok how do i do this...)</p>\n<p style=\"color: #1f9400\">JAKE: (Aw frig no time to think here i go!!!)</p>\n<p style=\"color: #f2a400\">DIRK: Jake.</p>",
    "flash": false,
    "javascript": false,
    "author": "THE HUSS",
    "commited": true
}