{
    "version": 0,
    "page": 3029,
    "commands": [
        {
            "command": "Dave: Duplicate disc. ",
            "link": "/story/3030"
        }
    ],
    "media": [
        {
            "file": "03028.gif",
            "folder": "0"
        }
    ],
    "text": null,
    "pesterlog": "<p style=\"color: #4ac925\">GG: well youre from the future right?</p>\n<p style=\"color: #4ac925\">GG: dont you know already if itll work?</p>\n<p style=\"color: #e00707\">TG: yeah more or less</p>\n<p style=\"color: #e00707\">TG: i never really studied how it went down all that closely</p>\n<p style=\"color: #e00707\">TG: i just figured when the time came to sort it out the right thing to do would be obvious</p>\n<p style=\"color: #e00707\">TG: like it is now</p>\n<p style=\"color: #e00707\">TG: managing the loops is a balance of careful planning and just rolling with your in the moment decisions</p>\n<p style=\"color: #e00707\">TG: and trusting they were the ones you were always supposed to make</p>\n<p style=\"color: #e00707\">TG: by now im pretty used to having my intuition woven into the fabric of the alpha timeline</p>\n<p style=\"color: #4ac925\">GG: pretty smooth dave</p>\n<p style=\"color: #e00707\">TG: yeah i know</p>\n<p style=\"color: #4ac925\">GG: shades for everybody</p>\n<p style=\"color: #4ac925\">GG: 8) 8)</p>",
    "flash": false,
    "javascript": false,
    "author": "THE HUSS",
    "commited": true
}