{
    "version": 0,
    "page": 6321,
    "commands": [
        {
            "command": "[A6A6I1] ====> ",
            "link": "/story/6322"
        }
    ],
    "media": [
        {
            "file": "06319.gif",
            "folder": "0"
        }
    ],
    "text": null,
    "pesterlog": "<p style=\"color: #e00707\">DAVE: how do we make it so it can damage him</p>\n<p style=\"color: #4ac925\">JADE:</span> <span style=\"color: #000000\">it needs a special ingredient</p>\n<p style=\"color: #4ac925\">JADE:</span> <span style=\"color: #000000\">something which represents his only known weakness, but hasnt been properly weaponized</p>\n<p style=\"color: #e00707\">DAVE: and you know what that is</p>\n<p style=\"color: #4ac925\">JADE:</span> <span style=\"color: #000000\">i do</p>\n<p style=\"color: #e00707\">DAVE: how</p>\n<p style=\"color: #4ac925\">JADE:</span> <span style=\"color: #000000\">i get all my intelligence on such matters from the old lady</p>\n<p style=\"color: #4ac925\">JADE:</span> <span style=\"color: #000000\">shes had centuries to hatch a plan to settle her score</p>\n<p style=\"color: #4ac925\">JADE:</span> <span style=\"color: #000000\">over time shes uncovered many secrets about him</p>\n<p style=\"color: #e00707\">DAVE: i dont understand how this is working</p>\n<p style=\"color: #e00707\">DAVE: is she piping all these secrets into your brain</p>\n<p style=\"color: #e00707\">DAVE: along with the evil</p>\n<p style=\"color: #4ac925\">JADE:</span> <span style=\"color: #000000\">that is not relevant!</p>\n<p style=\"color: #e00707\">DAVE: fair enough</p>\n<p style=\"color: #e00707\">DAVE: i guess technically almost nothing is relevant to the dude youre barking orders to</p>\n<p style=\"color: #e00707\">DAVE: literal barking because of dogginess</p>\n<p style=\"color: #4ac925\">JADE:</span> <span style=\"color: #000000\">bark bark bark!!!</p>\n<p style=\"color: #e00707\">DAVE: yes exactly like that</p>\n<p style=\"color: #e00707\">DAVE: thank you for participating in the joke</p>\n<p style=\"color: #e00707\">DAVE: now what is this special ingredient and where do we get it</p>\n<p style=\"color: #4ac925\">JADE:</span> <span style=\"color: #000000\">i already have it right here</p>\n<p style=\"color: #e00707\">DAVE: oh yeah?</p>\n<p style=\"color: #4ac925\">JADE:</span> <span style=\"color: #000000\">in fact ive had it for about as long as i can remember</p>\n<p style=\"color: #4ac925\">JADE:</span> <span style=\"color: #000000\">it was right under my doggy snout all along</p>",
    "flash": false,
    "javascript": false,
    "author": "THE HUSS",
    "commited": true
}