{
    "version": 0,
    "page": 7583,
    "commands": [
        {
            "command": "[A6A6I5] ====> ",
            "link": "/story/7584"
        }
    ],
    "media": [
        {
            "file": "07579.gif",
            "folder": "0"
        }
    ],
    "text": null,
    "pesterlog": "<p style=\"color: #e00707\">ARQUIUSPRITE: <img border=\"0\" src=\"/images/storyfiles/hs2/scraps/arquius_shades.png\"/> Abra cafiddling dabra you silly shootnerds</p>\n<p style=\"color: #e00707\">ARQUIUSPRITE: <img border=\"0\" src=\"/images/storyfiles/hs2/scraps/arquius_shades.png\"/> My e%ceedingly STRONG work as the party's premier bodybuilding hacker is done</p>\n<p style=\"color: #e00707\">ARQUIUSPRITE: <img border=\"0\" src=\"/images/storyfiles/hs2/scraps/arquius_shades.png\"/> Off I go</p>\n<p style=\"color: #00d5f2\">JANE: ...</p>",
    "flash": false,
    "javascript": false,
    "author": "THE HUSS",
    "commited": true
}