{
    "version": 0,
    "page": 7889,
    "commands": [
        {
            "command": "[A6A6I5] ====> ",
            "link": "/story/7890"
        }
    ],
    "media": [
        {
            "file": "07885.gif",
            "folder": "0"
        }
    ],
    "text": null,
    "pesterlog": "<p style=\"color: #4ac925\">JADE: well.......</p>\n<p style=\"color: #4ac925\">JADE: not that it isnt fun talking about these cool space things</p>\n<p style=\"color: #4ac925\">JADE: and</p>\n<p style=\"color: #4ac925\">JADE: i know you said my real body isnt supposed to be waking up yet, wherever and whenever it is</p>\n<p style=\"color: #4ac925\">JADE: but to tell you the truth...</p>\n<p style=\"color: #4ac925\">JADE: i would really love to get going and see my friends again!</p>\n<p style=\"color: #4ac925\">JADE: dont you have the power to wake me up?</p>\n<p style=\"color: #4ac925\">JADE: the other calliope said she has that power</p>\n<p style=\"color: #ff0000\">CALLIOPE: i do have that power.</p>\n<p style=\"color: #4ac925\">JADE: oh</p>\n<p style=\"color: #4ac925\">JADE: soooooo</p>\n<p style=\"color: #4ac925\">JADE: could you please wake me up then?</p>\n<p style=\"color: #ff0000\">CALLIOPE: no.</p>\n<p style=\"color: #4ac925\">JADE: aw</p>\n<p style=\"color: #4ac925\">JADE: why not!</p>\n<p style=\"color: #ff0000\">CALLIOPE: i told you.</p>\n<p style=\"color: #ff0000\">CALLIOPE: it is not time yet.</p>\n<p style=\"color: #ff0000\">CALLIOPE: we must reach our destination first, in order for the requisite time to flow correctly.</p>\n<p style=\"color: #ff0000\">CALLIOPE: only then.</p>\n<p style=\"color: #4ac925\">JADE: maaaan</p>\n<p style=\"color: #4ac925\">JADE: &gt;:(</p>\n<p style=\"color: #ff0000\">CALLIOPE: why the hurry?</p>\n<p style=\"color: #ff0000\">CALLIOPE: you have already proven your heroism in the moments when it was needed most.</p>\n<p style=\"color: #ff0000\">CALLIOPE: it is important to know when the greatest good is best served by remaining dormant.</p>\n<p style=\"color: #ff0000\">CALLIOPE: whether that burden is for close to eternity, or only a few more minutes.</p>\n<p style=\"color: #ff0000\">CALLIOPE: it is something to learn as a space player.</p>\n<p style=\"color: #ff0000\">CALLIOPE: space falls back. it yields. hosts the play silently.</p>\n<p style=\"color: #ff0000\">CALLIOPE: then, it roars to life when its time comes, showing all who is really the master.</p>\n<p style=\"color: #ff0000\">CALLIOPE: and so too when the time comes, it collapses in on itself, taking all else with it.</p>",
    "flash": false,
    "javascript": false,
    "author": "THE HUSS",
    "commited": true
}