{
    "version": 0,
    "page": 2941,
    "commands": [
        {
            "command": "==> ",
            "link": "/story/2942"
        }
    ],
    "media": [
        {
            "file": "02940.gif",
            "folder": "0"
        }
    ],
    "text": null,
    "pesterlog": "<p style=\"color: #626262\">CG: ANYWAY, THAT'S WHAT HAPPENED, AND THAT'S WHY YOU ARE SUCH A DISGRACE.</p>\n<p style=\"color: #626262\">CG: THIS IS PROBABLY THE LAST TIME I WILL EVER EXPLAIN ALL THIS STUFF TO YOU, BECAUSE I CAN'T IMAGINE IT WILL HELP MY HEADACHE MUCH TO REPEAT MYSELF.</p>\n<p style=\"color: #626262\">CG: I BET IT'LL BE PRETTY FRUSTRATING FOR YOU IN THE PAST!</p>\n<p style=\"color: #0715cd\">EB: i suppose it was...</p>\n<p style=\"color: #0715cd\">EB: but meh, it is all water under the bridge.</p>\n<p style=\"color: #0715cd\">EB: which is where trolls and their shenanigans belong!</p>\n<p style=\"color: #626262\">CG: HA HA! I'M LAUGHING MY ASS OFF AT YOUR FUNNY FUCKING JOKE.</p>\n<p style=\"color: #626262\">CG: I HOPE THIS IS THE CALIBER OF HUMOR I CAN EXPECT FROM YOU IN THE FUTURE-PAST, EGBERT.</p>\n<p style=\"color: #626262\">CG: IT'LL BE A REAL TREAT TROLLING YOU WITH MORE OF THOSE NUB SLAPPERS TO LOOK FORWARD TO!</p>\n<p style=\"color: #0715cd\">EB: oh, there will be lots of great material. just wait until i start handing out rabbits, you will love that.</p>\n<p style=\"color: #626262\">CG: WOW, WHAT A CRYPTIC STATEMENT.</p>\n<p style=\"color: #626262\">CG: CHECK THIS OUT, I DON'T GIVE A FUCK.</p>\n<p style=\"color: #626262\">CG: ANYWAY, GUESS I'LL GET GOING AND LET YOU DIE IN YOUR FIRE, WHICH YOU REALLY SHOULD, BUT YOU'RE OBVIOUSLY NOT GOING TO FOR SOME REASON.</p>\n<p style=\"color: #626262\">CG: I'VE GOT TO REWIND THE TAPE ON THIS CLUSTERFUCK AND FIGURE OUT WHAT WENT WRONG.</p>\n<p style=\"color: #0715cd\">EB: yeah, i should get going too.</p>\n<p style=\"color: #0715cd\">EB: my friend is pestering me, and i doubt she likes to be kept waiting.</p>\n<p style=\"color: #0715cd\">EB: (she is sort of the bossy type!)</p>\n<p style=\"color: #626262\">CG: WHY WOULD I CARE ABOUT YOUR DUMB HUMAN FRIEND AND HER PETULANT, MEANINGLESS DEMANDS.</p>\n<p style=\"color: #626262\">CG: WHAT COULD THAT POSSIBLY HAVE TO DO WITH ME.</p>\n<p style=\"color: #0715cd\">EB: ummm...</p>\n<p style=\"color: #0715cd\">EB: yeah, you're right, it is probably of no significance to you whatsoever.</p>\n<p style=\"color: #0715cd\">EB: (hehehehe)</p>\n<p style=\"color: #626262\">CG: A;SLDKJFSDLKFJS;LDJFLK;J</p>\n<p style=\"color: #626262\">CG: HERE, JOHN HUMAN DIPSHIT.</p>\n<p style=\"color: #626262\">CG: HAVE A SECOND AND PENULTIMATE FUCK YOU:</p>\n<p style=\"color: #626262\">CG: \"FUCK\"</p>\n<p style=\"color: #626262\">CG: \"YOU\"</p>\n<p style=\"color: #626262\">CG: MAY IT MARK THE SECOND OF MANY TO COME, AND THE MAGNIFICENT DENOUEMENT TO MANY RECEIVED.</p>\n<p style=\"color: #626262\">CG: TOGETHER WE JUST TUGGED AT THE BOW TO UNRAVEL A PRESENT FULL OF GO FUCK YOURSELF.</p>\n<p style=\"color: #626262\">CG: HAPPY WRIGGLING DAY YOU UGLY PILE OF TRASH.</p>\n\n-- carcinoGeneticist <span style=\"color: #626262\">[CG]</span> ceased trolling ectoBiologist <span style=\"color: #0715cd\">[EB]</span> --</p>",
    "flash": false,
    "javascript": false,
    "author": "THE HUSS",
    "commited": true
}