{
    "version": 0,
    "page": 2205,
    "commands": [
        {
            "command": "======> ",
            "link": "/story/2206"
        }
    ],
    "media": [
        {
            "file": "02205.gif",
            "folder": "0"
        }
    ],
    "text": "<p class=\"o-story_text type-rg type-hs-small--md type-center line-caption line-copy--md pad-x-0 pad-x-lg--md pad-b-lg\">You go down the like fifty million stairs to her nest below. You wonder if any other kid on the planet has such a high maintenance lusus? You DOUBT it.</p>",
    "pesterlog": null,
    "flash": false,
    "javascript": false,
    "author": "THE HUSS",
    "commited": true
}