{
    "version": 0,
    "page": 7219,
    "commands": [
        {
            "command": "[A6A6I4] ====> ",
            "link": "/story/7220"
        }
    ],
    "media": [
        {
            "file": "07216.gif",
            "folder": "0"
        }
    ],
    "text": null,
    "pesterlog": "<p style=\"color: #0715cd\">JOHN: so yeah, time to go get that ring.</p>\n<p style=\"color: #0715cd\">JOHN: i don't know what's going to happen to you all once i change stuff...</p>\n<p style=\"color: #0715cd\">JOHN: maybe you'll stop existing? i don't have a damn clue, to be honest.</p>\n<p style=\"color: #0715cd\">JOHN: but just so you know, you will always keep existing in my heart.</p>\n<p style=\"color: #0715cd\">JOHN: bye!</p>",
    "flash": false,
    "javascript": false,
    "author": "THE HUSS",
    "commited": true
}